{
  "count_url2":"http://a39d49540865649989abbc5d2f5c409b-4d2c93a40177d71e.elb.eu-west-2.amazonaws.com/es/_count",
  "type_registry":{
    "es_held_count":{
      "#type": "http_request",
      "url": "{%.count_url2}",
      "method": "POST",
      "headers":{
        "Content-Type": "application/json",
        "Authorization": "Basic ZWxhc3RpYzpnNG03Tm05d2wwUjEwTk1ibjlEOU9OMjI="
      },
      "body":{
        "query":{
          "term":{
            "$.source.repository.@admin.id": "&.Id"
          }
        }
      },
      "allow": 200,
      "timeout": 4000,
      "require_allowed": true,
      "require_response": true
    }
  }
}